light_speed/__init__.py
light_speed-0.1.3.dist-info/LICENSE
light_speed-0.1.3.dist-info/METADATA
light_speed-0.1.3.dist-info/WHEEL
light_speed-0.1.3.dist-info/top_level.txt
light_speed-0.1.3.dist-info/RECORD
