Metadata-Version: 2.2
Name: light_speed
Version: 0.1.3
Summary: A comprehensive physics package for light speed and real-world calculations
Home-page: https://github.com/ishanoshada/light-speed
Author: Ishan Oshada
Author-email: ishan.kodithuwakku.offical@gmail.com
Project-URL: Bug Tracker, https://github.com/ishanoshada/light-speed/issues
Project-URL: Source Code, https://github.com/ishanoshada/light-speed
Keywords: relativity physics light-speed optics
Classifier: Programming Language :: Python :: 3
Classifier: License :: OSI Approved :: MIT License
Classifier: Operating System :: OS Independent
Classifier: Intended Audience :: Science/Research
Classifier: Topic :: Scientific/Engineering :: Physics
License-File: LICENSE
Requires-Dist: numpy
Dynamic: author
Dynamic: author-email
Dynamic: classifier
Dynamic: description
Dynamic: description-content-type
Dynamic: home-page
Dynamic: keywords
Dynamic: project-url
Dynamic: requires-dist
Dynamic: summary
